xenlib/__init__.py
xenlib/ssteal.py
xenlib-0.1.1.dist-info/METADATA
xenlib-0.1.1.dist-info/WHEEL
xenlib-0.1.1.dist-info/top_level.txt
xenlib-0.1.1.dist-info/RECORD
