Metadata-Version: 2.4
Name: xenlib
Version: 0.1.1
Summary: Essentials...
